zfpkm/__init__.py
zfpkm/approx.py
zfpkm/density.py
zfpkm/peak_finder.py
zfpkm/plot.py
zfpkm/types.py
zfpkm-1.0.3.dist-info/WHEEL
zfpkm-1.0.3.dist-info/METADATA
zfpkm-1.0.3.dist-info/RECORD
