Metadata-Version: 2.3
Name: zfpkm
Version: 1.0.3
Summary: Find active genes in bulk RNA-seq data
Author: Josh Loecker
Author-email: Josh Loecker <joshloecker@icloud.com>
License: MIT
Classifier: Development Status :: 5 - Production/Stable
Classifier: Intended Audience :: Science/Research
Classifier: License :: OSI Approved :: MIT License
Classifier: Operating System :: OS Independent
Classifier: Programming Language :: Python :: 3
Classifier: Programming Language :: Python :: 3 :: Only
Classifier: Programming Language :: Python :: 3.10
Classifier: Programming Language :: Python :: 3.11
Classifier: Programming Language :: Python :: 3.12
Classifier: Programming Language :: Python :: 3.13
Classifier: Programming Language :: Python :: 3.14
Classifier: Programming Language :: Python :: Free Threading :: 3 - Stable
Classifier: Topic :: Scientific/Engineering :: Bio-Informatics
Classifier: Topic :: Scientific/Engineering :: Mathematics
Requires-Dist: loguru>=0.7.3
Requires-Dist: matplotlib>=3.7.3
Requires-Dist: numpy>=1.21.0
Requires-Dist: pandas>=2.0.0
Requires-Python: >=3.10
